[
  {
    "year": 1225,
    "event": "Nhà Trần thành lập (1225). Lý Chiêu Hoàng nhường ngôi cho Trần Cảnh, mở đầu triều Trần. Sự kiện này có là Mở ra thời kỳ hưng thịnh, nổi bật với ba lần kháng Mông-Nguyên",
    "story": "",
    "persons": [
      "Lý Chiêu Hoàng",
      "Trần Cảnh"
    ],
    "places": []
  },
  {
    "year": 1225,
    "event": "B1. gắn mốc 1225 với Nhà Trần thành lập. B2. nêu diễn biến trọng tâm – \"Lý Chiêu Hoàng nhường ngôi cho Trần Cảnh, mở đầu triều Trần.\". B3. kết luận – Mở ra thời kỳ hưng thịnh, nổi bật với ba lần kháng Mông-Nguyên",
    "story": "",
    "persons": [
      "Lý Chiêu Hoàng",
      "Trần Cảnh"
    ],
    "places": []
  },
  {
    "year": 1225,
    "event": "Câu hỏi nhắm tới sự kiện Nhà Trần thành lập (1225). Cốt lõi. Lý Chiêu Hoàng nhường ngôi cho Trần Cảnh, mở đầu triều Trần.. . Mở ra thời kỳ hưng thịnh, nổi bật với ba lần kháng Mông-Nguyên.. Trả lời sẽ nêu rõ mốc, diễn biến chính và",
    "story": "",
    "persons": [
      "Lý Chiêu Hoàng",
      "Trần Cảnh"
    ],
    "places": []
  },
  {
    "year": 1284,
    "event": "B1. gắn mốc 1284 với Hịch tướng sĩ. B2. nêu diễn biến trọng tâm – \"Trần Hưng Đạo soạn Hịch tướng sĩ khích lệ quân dân trước kháng chiến lần 2.\". B3. kết luận – Tác phẩm quân sự – chính trị cổ vũ mạnh mẽ",
    "story": "",
    "persons": [
      "Trần Hưng Đạo"
    ],
    "places": []
  },
  {
    "year": 1284,
    "event": "Hịch tướng sĩ (1284). Trần Hưng Đạo soạn Hịch tướng sĩ khích lệ quân dân trước kháng chiến lần 2. Sự kiện này có là Tác phẩm quân sự – chính trị cổ vũ mạnh mẽ",
    "story": "",
    "persons": [
      "Trần Hưng Đạo"
    ],
    "places": []
  },
  {
    "year": 1284,
    "event": "Câu hỏi nhắm tới sự kiện Hịch tướng sĩ (1284). Cốt lõi. Trần Hưng Đạo soạn Hịch tướng sĩ khích lệ quân dân trước kháng chiến lần 2.. . Tác phẩm quân sự – chính trị cổ vũ mạnh mẽ.. Trả lời sẽ nêu rõ mốc, diễn biến chính và",
    "story": "",
    "persons": [
      "Trần Hưng Đạo"
    ],
    "places": []
  },
  {
    "year": 1400,
    "event": "B1. gắn mốc 1400 với Hồ Quý Ly lập nhà Hồ. B2. nêu diễn biến trọng tâm – \"Hồ Quý Ly cải cách mạnh, đổi quốc hiệu Đại Ngu.\". B3. kết luận – Cải cách táo bạo nhưng không vững bền, dẫn tới họa xâm lăng",
    "story": "",
    "persons": [
      "Hồ Quý Ly"
    ],
    "places": []
  },
  {
    "year": 1400,
    "event": "Hồ Quý Ly lập nhà Hồ diễn ra năm 1400. . Hồ Quý Ly cải cách mạnh, đổi quốc hiệu Đại Ngu.. . Cải cách táo bạo nhưng không vững bền, dẫn tới họa xâm lăng",
    "story": "",
    "persons": [
      "Hồ Quý Ly"
    ],
    "places": []
  },
  {
    "year": 1400,
    "event": "Câu hỏi nhắm tới sự kiện Hồ Quý Ly lập nhà Hồ (1400). Cốt lõi. Hồ Quý Ly cải cách mạnh, đổi quốc hiệu Đại Ngu.. . Cải cách táo bạo nhưng không vững bền, dẫn tới họa xâm lăng.. Trả lời sẽ nêu rõ mốc, diễn biến chính và",
    "story": "",
    "persons": [
      "Hồ Quý Ly"
    ],
    "places": []
  },
  {
    "year": 1400,
    "event": "Hồ Quý Ly lập nhà Hồ (1400). Hồ Quý Ly cải cách mạnh, đổi quốc hiệu Đại Ngu. Sự kiện này có là Cải cách táo bạo nhưng không vững bền, dẫn tới họa xâm lăng",
    "story": "",
    "persons": [
      "Hồ Quý Ly"
    ],
    "places": []
  },
  {
    "year": 1771,
    "event": "Câu hỏi nhắm tới sự kiện Khởi nghĩa Tây Sơn bùng nổ (1771). Cốt lõi. Anh em Tây Sơn khởi nghĩa, chống các thế lực Trịnh – Nguyễn.. . Đặt nền tảng thống nhất, cải cách mạnh mẽ.. Trả lời sẽ nêu rõ mốc, diễn biến chính và",
    "story": "",
    "persons": [],
    "places": []
  },
  {
    "year": 1771,
    "event": "Khởi nghĩa Tây Sơn bùng nổ (1771). Anh em Tây Sơn khởi nghĩa, chống các thế lực Trịnh – Nguyễn. Sự kiện này có là Đặt nền tảng thống nhất, cải cách mạnh mẽ",
    "story": "",
    "persons": [],
    "places": []
  },
  {
    "year": 1771,
    "event": "B1. gắn mốc 1771 với Khởi nghĩa Tây Sơn bùng nổ. B2. nêu diễn biến trọng tâm – \"Anh em Tây Sơn khởi nghĩa, chống các thế lực Trịnh – Nguyễn.\". B3. kết luận – Đặt nền tảng thống nhất, cải cách mạnh mẽ",
    "story": "",
    "persons": [],
    "places": []
  },
  {
    "year": 1945,
    "event": "Cách mạng Tháng Tám và Tuyên ngôn Độc lập (1945). Tổng khởi nghĩa giành chính quyền. ngày 2 tháng 9 năm 1945, Hồ Chí Minh đọc Tuyên ngôn Độc lập. Sự kiện này có là Khai sinh nước Việt Nam Dân chủ Cộng hòa, chấm dứt chế độ thực dân – phong kiến",
    "story": "",
    "persons": [
      "Hồ Chí Minh"
    ],
    "places": []
  },
  {
    "year": 1945,
    "event": "B1. gắn mốc 1945 với Cách mạng Tháng Tám và Tuyên ngôn Độc lập. B2. nêu diễn biến trọng tâm – \"Tổng khởi nghĩa giành chính quyền. ngày 2 tháng 9 năm 1945, Hồ Chí Minh đọc Tuyên ngôn Độc lập.\". B3. kết luận – Khai sinh nước Việt Nam Dân chủ Cộng hòa, chấm dứt chế độ thực dân – phong kiến",
    "story": "",
    "persons": [
      "Hồ Chí Minh"
    ],
    "places": []
  },
  {
    "year": 1945,
    "event": "Bối cảnh. Cách mạng Tháng Tám và Tuyên ngôn Độc lập thuộc Cách mạng 1945, địa điểm Hà Nội. Cốt lõi. Tổng khởi nghĩa giành chính quyền. ngày 2 tháng 9 năm 1945, Hồ Chí Minh đọc Tuyên ngôn Độc lập.. . Khai sinh nước Việt Nam Dân chủ Cộng hòa, chấm dứt chế độ thực dân – phong kiến.. Sẽ tóm lược rõ ràng",
    "story": "",
    "persons": [
      "Hồ Chí Minh"
    ],
    "places": [
      "Hà Nội"
    ]
  },
  {
    "year": 1945,
    "event": "Câu hỏi nhắm tới sự kiện Cách mạng Tháng Tám và Tuyên ngôn Độc lập (1945). Cốt lõi. Tổng khởi nghĩa giành chính quyền. ngày 2 tháng 9 năm 1945, Hồ Chí Minh đọc Tuyên ngôn Độc lập.. . Khai sinh nước Việt Nam Dân chủ Cộng hòa, chấm dứt chế độ thực dân – phong kiến.. Trả lời sẽ nêu rõ mốc, diễn biến chính và",
    "story": "",
    "persons": [
      "Hồ Chí Minh"
    ],
    "places": []
  },
  {
    "year": 1885,
    "event": "Phong trào Cần Vương (1885). Vua Hàm Nghi hạ Chiếu Cần Vương, kêu gọi chống Pháp. Sự kiện này có là Lan rộng kháng chiến chống Pháp cuối thế kỷ XIX",
    "story": "",
    "persons": [],
    "places": []
  },
  {
    "year": 1885,
    "event": "Câu hỏi nhắm tới sự kiện Phong trào Cần Vương (1885). Cốt lõi. Vua Hàm Nghi hạ Chiếu Cần Vương, kêu gọi chống Pháp.. . Lan rộng kháng chiến chống Pháp cuối thế kỷ XIX.. Trả lời sẽ nêu rõ mốc, diễn biến chính và",
    "story": "",
    "persons": [],
    "places": []
  },
  {
    "year": 1885,
    "event": "B1. gắn mốc 1885 với Phong trào Cần Vương. B2. nêu diễn biến trọng tâm – \"Vua Hàm Nghi hạ Chiếu Cần Vương, kêu gọi chống Pháp.\". B3. kết luận – Lan rộng kháng chiến chống Pháp cuối thế kỷ XIX",
    "story": "",
    "persons": [],
    "places": []
  },
  {
    "year": 1858,
    "event": "Câu hỏi nhắm tới sự kiện Liên quân Pháp – Tây Ban Nha tấn công Đà Nẵng (1858). Cốt lõi. Mở đầu cuộc chiến xâm lược của Pháp tại Việt Nam.. . Khởi đầu thời kỳ thực dân xâm lược kéo dài gần một thế kỷ.. Trả lời sẽ nêu rõ mốc, diễn biến chính và",
    "story": "",
    "persons": [],
    "places": [
      "Đà Nẵng"
    ]
  },
  {
    "year": 1858,
    "event": "Liên quân Pháp – Tây Ban Nha tấn công Đà Nẵng (1858). Mở đầu cuộc chiến xâm lược của Pháp tại Việt Nam. Sự kiện này có là Khởi đầu thời kỳ thực dân xâm lược kéo dài gần một thế kỷ",
    "story": "",
    "persons": [],
    "places": [
      "Đà Nẵng"
    ]
  },
  {
    "year": 1858,
    "event": "B1. gắn mốc 1858 với Liên quân Pháp – Tây Ban Nha tấn công Đà Nẵng. B2. nêu diễn biến trọng tâm – \"Mở đầu cuộc chiến xâm lược của Pháp tại Việt Nam.\". B3. kết luận – Khởi đầu thời kỳ thực dân xâm lược kéo dài gần một thế kỷ",
    "story": "",
    "persons": [],
    "places": [
      "Đà Nẵng"
    ]
  },
  {
    "year": 968,
    "event": "Câu hỏi nhắm tới sự kiện Đinh Bộ Lĩnh dẹp loạn 12 sứ quân, lập Đại Cồ Việt (968). Cốt lõi. Đinh Bộ Lĩnh thống nhất cát cứ, lên ngôi Hoàng đế, đặt quốc hiệu Đại Cồ Việt.. . Chấm dứt cát cứ, xây dựng nhà nước trung ương tập quyền đầu tiên sau độc lập.. Trả lời sẽ nêu rõ mốc, diễn biến chính và",
    "story": "",
    "persons": [
      "Đinh Bộ Lĩnh"
    ],
    "places": []
  },
  {
    "year": 968,
    "event": "Đinh Bộ Lĩnh dẹp loạn 12 sứ quân, lập Đại Cồ Việt (968). Đinh Bộ Lĩnh thống nhất cát cứ, lên ngôi Hoàng đế, đặt quốc hiệu Đại Cồ Việt. Sự kiện này có là Chấm dứt cát cứ, xây dựng nhà nước trung ương tập quyền đầu tiên sau độc lập",
    "story": "",
    "persons": [
      "Đinh Bộ Lĩnh"
    ],
    "places": []
  },
  {
    "year": 968,
    "event": "B1. gắn mốc 968 với Đinh Bộ Lĩnh dẹp loạn 12 sứ quân, lập Đại Cồ Việt. B2. nêu diễn biến trọng tâm – \"Đinh Bộ Lĩnh thống nhất cát cứ, lên ngôi Hoàng đế, đặt quốc hiệu Đại Cồ Việt.\". B3. kết luận – Chấm dứt cát cứ, xây dựng nhà nước trung ương tập quyền đầu tiên sau độc lập",
    "story": "",
    "persons": [
      "Đinh Bộ Lĩnh"
    ],
    "places": []
  },
  {
    "year": 1972,
    "event": "B1. gắn mốc 1972 với Chiến dịch 'Điện Biên Phủ trên không'. B2. nêu diễn biến trọng tâm – \"Quân dân miền Bắc đánh bại chiến dịch ném bom B-52 cuối 1972.\". B3. kết luận – Buộc Mỹ đàm phán, tiền đề Hiệp định Paris",
    "story": "",
    "persons": [],
    "places": [
      "Điện Biên Phủ"
    ]
  },
  {
    "year": 1972,
    "event": "Chiến dịch 'Điện Biên Phủ trên không' (1972). Quân dân miền Bắc đánh bại chiến dịch ném bom B-52 cuối 1972. Sự kiện này có là Buộc Mỹ đàm phán, tiền đề Hiệp định Paris",
    "story": "",
    "persons": [],
    "places": [
      "Điện Biên Phủ"
    ]
  },
  {
    "year": 1972,
    "event": "Câu hỏi nhắm tới sự kiện Chiến dịch 'Điện Biên Phủ trên không' (1972). Cốt lõi. Quân dân miền Bắc đánh bại chiến dịch ném bom B-52 cuối 1972.. . Buộc Mỹ đàm phán, tiền đề Hiệp định Paris.. Trả lời sẽ nêu rõ mốc, diễn biến chính và",
    "story": "",
    "persons": [],
    "places": [
      "Điện Biên Phủ"
    ]
  },
  {
    "year": 980,
    "event": "Lê Hoàn lên ngôi (Nhà Tiền Lê) diễn ra năm 980. . Lê Hoàn được suy tôn sau biến cố cuối triều Đinh.. . Ổn định triều chính, chuẩn bị chống Tống",
    "story": "",
    "persons": [
      "Lê Hoàn"
    ],
    "places": []
  },
  {
    "year": 980,
    "event": "Lê Hoàn lên ngôi (Nhà Tiền Lê) (980). Lê Hoàn được suy tôn sau biến cố cuối triều Đinh. Sự kiện này có là Ổn định triều chính, chuẩn bị chống Tống",
    "story": "",
    "persons": [
      "Lê Hoàn"
    ],
    "places": []
  },
  {
    "year": 980,
    "event": "B1. gắn mốc 980 với Lê Hoàn lên ngôi (Nhà Tiền Lê). B2. nêu diễn biến trọng tâm – \"Lê Hoàn được suy tôn sau biến cố cuối triều Đinh.\". B3. kết luận – Ổn định triều chính, chuẩn bị chống Tống",
    "story": "",
    "persons": [
      "Lê Hoàn"
    ],
    "places": []
  },
  {
    "year": 980,
    "event": "Câu hỏi nhắm tới sự kiện Lê Hoàn lên ngôi (Nhà Tiền Lê) (980). Cốt lõi. Lê Hoàn được suy tôn sau biến cố cuối triều Đinh.. . Ổn định triều chính, chuẩn bị chống Tống.. Trả lời sẽ nêu rõ mốc, diễn biến chính và",
    "story": "",
    "persons": [
      "Lê Hoàn"
    ],
    "places": []
  },
  {
    "year": 931,
    "event": "Dương Đình Nghệ đánh tan quân Nam Hán (931). Dương Đình Nghệ lãnh đạo nghĩa quân, đẩy lui quân Nam Hán. Sự kiện này có là Củng cố nền tự chủ, tạo tiền đề cho thời Ngô",
    "story": "",
    "persons": [
      "Dương Đình Nghệ"
    ],
    "places": []
  },
  {
    "year": 931,
    "event": "B1. gắn mốc 931 với Dương Đình Nghệ đánh tan quân Nam Hán. B2. nêu diễn biến trọng tâm – \"Dương Đình Nghệ lãnh đạo nghĩa quân, đẩy lui quân Nam Hán.\". B3. kết luận – Củng cố nền tự chủ, tạo tiền đề cho thời Ngô",
    "story": "",
    "persons": [
      "Dương Đình Nghệ"
    ],
    "places": []
  },
  {
    "year": 931,
    "event": "Câu hỏi nhắm tới sự kiện Dương Đình Nghệ đánh tan quân Nam Hán (931). Cốt lõi. Dương Đình Nghệ lãnh đạo nghĩa quân, đẩy lui quân Nam Hán.. . Củng cố nền tự chủ, tạo tiền đề cho thời Ngô.. Trả lời sẽ nêu rõ mốc, diễn biến chính và",
    "story": "",
    "persons": [
      "Dương Đình Nghệ"
    ],
    "places": []
  },
  {
    "year": 1973,
    "event": "Câu hỏi nhắm tới sự kiện Hiệp định Paris (1973). Cốt lõi. Hiệp định chấm dứt chiến tranh, lập lại hòa bình ở Việt Nam.. . Mỹ rút quân khỏi Việt Nam.. Trả lời sẽ nêu rõ mốc, diễn biến chính và",
    "story": "",
    "persons": [],
    "places": []
  },
  {
    "year": 1973,
    "event": "Hiệp định Paris (1973). Hiệp định chấm dứt chiến tranh, lập lại hòa bình ở Việt Nam. Sự kiện này có là Mỹ rút quân khỏi Việt Nam",
    "story": "",
    "persons": [],
    "places": []
  },
  {
    "year": 1973,
    "event": "B1. gắn mốc 1973 với Hiệp định Paris. B2. nêu diễn biến trọng tâm – \"Hiệp định chấm dứt chiến tranh, lập lại hòa bình ở Việt Nam.\". B3. kết luận – Mỹ rút quân khỏi Việt Nam",
    "story": "",
    "persons": [],
    "places": []
  },
  {
    "year": 905,
    "event": "Khúc Thừa Dụ dựng chính quyền tự chủ (905). Khúc Thừa Dụ nắm quyền ở Tống Bình, khôi phục quyền tự chủ sau thời Bắc thuộc muộn. Sự kiện này có là Mở đầu thời kỳ tự chủ của người Việt sau nhiều thế kỷ bị phương Bắc cai trị",
    "story": "",
    "persons": [
      "Khúc Thừa Dụ"
    ],
    "places": []
  },
  {
    "year": 905,
    "event": "B1. gắn mốc 905 với Khúc Thừa Dụ dựng chính quyền tự chủ. B2. nêu diễn biến trọng tâm – \"Khúc Thừa Dụ nắm quyền ở Tống Bình, khôi phục quyền tự chủ sau thời Bắc thuộc muộn.\". B3. kết luận – Mở đầu thời kỳ tự chủ của người Việt sau nhiều thế kỷ bị phương Bắc cai trị",
    "story": "",
    "persons": [
      "Khúc Thừa Dụ"
    ],
    "places": []
  },
  {
    "year": 905,
    "event": "Câu hỏi nhắm tới sự kiện Khúc Thừa Dụ dựng chính quyền tự chủ (905). Cốt lõi. Khúc Thừa Dụ nắm quyền ở Tống Bình, khôi phục quyền tự chủ sau thời Bắc thuộc muộn.. . Mở đầu thời kỳ tự chủ của người Việt sau nhiều thế kỷ bị phương Bắc cai trị.. Trả lời sẽ nêu rõ mốc, diễn biến chính và",
    "story": "",
    "persons": [
      "Khúc Thừa Dụ"
    ],
    "places": []
  },
  {
    "year": 1418,
    "event": "Câu hỏi nhắm tới sự kiện Khởi nghĩa Lam Sơn bùng nổ (1418). Cốt lõi. Lê Lợi dựng cờ khởi nghĩa ở Lam Sơn chống quân Minh.. . Khởi đầu cuộc giải phóng dân tộc kéo dài gần 10 năm.. Trả lời sẽ nêu rõ mốc, diễn biến chính và",
    "story": "",
    "persons": [
      "Lê Lợi"
    ],
    "places": [
      "Lam Sơn"
    ]
  },
  {
    "year": 1418,
    "event": "Khởi nghĩa Lam Sơn bùng nổ (1418). Lê Lợi dựng cờ khởi nghĩa ở Lam Sơn chống quân Minh. Sự kiện này có là Khởi đầu cuộc giải phóng dân tộc kéo dài gần 10 năm",
    "story": "",
    "persons": [
      "Lê Lợi"
    ],
    "places": [
      "Lam Sơn"
    ]
  },
  {
    "year": 1418,
    "event": "B1. gắn mốc 1418 với Khởi nghĩa Lam Sơn bùng nổ. B2. nêu diễn biến trọng tâm – \"Lê Lợi dựng cờ khởi nghĩa ở Lam Sơn chống quân Minh.\". B3. kết luận – Khởi đầu cuộc giải phóng dân tộc kéo dài gần 10 năm",
    "story": "",
    "persons": [
      "Lê Lợi"
    ],
    "places": [
      "Lam Sơn"
    ]
  },
  {
    "year": 1075,
    "event": "B1. gắn mốc 1075 với Lý Thường Kiệt chủ động tiến công Ung–Khâm–Liêm. B2. nêu diễn biến trọng tâm – \"Quân Đại Việt tấn công trước để phá thế xâm lược của nhà Tống.\". B3. kết luận – Ngăn chặn nguy cơ xâm lược, thể hiện nghệ thuật quân sự chủ động",
    "story": "",
    "persons": [
      "Lý Thường Kiệt"
    ],
    "places": []
  },
  {
    "year": 1075,
    "event": "Lý Thường Kiệt chủ động tiến công Ung–Khâm–Liêm (1075). Quân Đại Việt tấn công trước để phá thế xâm lược của nhà Tống. Sự kiện này có là Ngăn chặn nguy cơ xâm lược, thể hiện nghệ thuật quân sự chủ động",
    "story": "",
    "persons": [
      "Lý Thường Kiệt"
    ],
    "places": []
  },
  {
    "year": 1075,
    "event": "Câu hỏi nhắm tới sự kiện Lý Thường Kiệt chủ động tiến công Ung–Khâm–Liêm (1075). Cốt lõi. Quân Đại Việt tấn công trước để phá thế xâm lược của nhà Tống.. . Ngăn chặn nguy cơ xâm lược, thể hiện nghệ thuật quân sự chủ động.. Trả lời sẽ nêu rõ mốc, diễn biến chính và",
    "story": "",
    "persons": [
      "Lý Thường Kiệt"
    ],
    "places": []
  },
  {
    "year": 1054,
    "event": "Câu hỏi nhắm tới sự kiện Đổi quốc hiệu thành Đại Việt (1054). Cốt lõi. Thời Lý Thánh Tông, quốc hiệu đổi từ Đại Cồ Việt sang Đại Việt.. . Khẳng định bản sắc và vị thế quốc gia độc lập.. Trả lời sẽ nêu rõ mốc, diễn biến chính và",
    "story": "",
    "persons": [
      "Lý Thánh Tông"
    ],
    "places": [
      "Đại Việt"
    ]
  },
  {
    "year": 1054,
    "event": "Đổi quốc hiệu thành Đại Việt (1054). Thời Lý Thánh Tông, quốc hiệu đổi từ Đại Cồ Việt sang Đại Việt. Sự kiện này có là Khẳng định bản sắc và vị thế quốc gia độc lập",
    "story": "",
    "persons": [
      "Lý Thánh Tông"
    ],
    "places": [
      "Đại Việt"
    ]
  },
  {
    "year": 1054,
    "event": "B1. gắn mốc 1054 với Đổi quốc hiệu thành Đại Việt. B2. nêu diễn biến trọng tâm – \"Thời Lý Thánh Tông, quốc hiệu đổi từ Đại Cồ Việt sang Đại Việt.\". B3. kết luận – Khẳng định bản sắc và vị thế quốc gia độc lập",
    "story": "",
    "persons": [
      "Lý Thánh Tông"
    ],
    "places": [
      "Đại Việt"
    ]
  },
  {
    "year": 1010,
    "event": "Chiếu dời đô (văn kiện) diễn ra năm 1010. . Văn kiện nêu lý do dời đô và tầm nhìn phát triển ở Đại La.. . Tư tưởng quy hoạch, tầm nhìn chiến lược thời Lý",
    "story": "",
    "persons": [],
    "places": []
  },
  {
    "year": 1010,
    "event": "Chiếu dời đô (văn kiện) (1010). Văn kiện nêu lý do dời đô và tầm nhìn phát triển ở Đại La. Sự kiện này có là Tư tưởng quy hoạch, tầm nhìn chiến lược thời Lý",
    "story": "",
    "persons": [],
    "places": []
  },
  {
    "year": 1010,
    "event": "B1. gắn mốc 1010 với Chiếu dời đô – dời đô ra Thăng Long. B2. nêu diễn biến trọng tâm – \"Vua Lý Thái Tổ ban Chiếu dời đô, dời kinh đô từ Hoa Lư ra Đại La (Thăng Long).\". B3. kết luận – Đặt nền móng cho Thăng Long – Hà Nội hơn một nghìn năm văn hiến",
    "story": "",
    "persons": [
      "Lý Thái Tổ"
    ],
    "places": [
      "Hà Nội",
      "Thăng Long"
    ]
  },
  {
    "year": 1010,
    "event": "Chiếu dời đô – dời đô ra Thăng Long (1010). Vua Lý Thái Tổ ban Chiếu dời đô, dời kinh đô từ Hoa Lư ra Đại La (Thăng Long). Sự kiện này có là Đặt nền móng cho Thăng Long – Hà Nội hơn một nghìn năm văn hiến",
    "story": "",
    "persons": [
      "Lý Thái Tổ"
    ],
    "places": [
      "Hà Nội",
      "Thăng Long"
    ]
  },
  {
    "year": 1010,
    "event": "B1. gắn mốc 1010 với Chiếu dời đô (văn kiện). B2. nêu diễn biến trọng tâm – \"Văn kiện nêu lý do dời đô và tầm nhìn phát triển ở Đại La.\". B3. kết luận – Tư tưởng quy hoạch, tầm nhìn chiến lược thời Lý",
    "story": "",
    "persons": [],
    "places": []
  },
  {
    "year": 1010,
    "event": "Câu hỏi nhắm tới sự kiện Chiếu dời đô – dời đô ra Thăng Long (1010). Cốt lõi. Vua Lý Thái Tổ ban Chiếu dời đô, dời kinh đô từ Hoa Lư ra Đại La (Thăng Long).. . Đặt nền móng cho Thăng Long – Hà Nội hơn một nghìn năm văn hiến.. Trả lời sẽ nêu rõ mốc, diễn biến chính và",
    "story": "",
    "persons": [
      "Lý Thái Tổ"
    ],
    "places": [
      "Hà Nội",
      "Thăng Long"
    ]
  },
  {
    "year": 1010,
    "event": "Câu hỏi nhắm tới sự kiện Chiếu dời đô (văn kiện) (1010). Cốt lõi. Văn kiện nêu lý do dời đô và tầm nhìn phát triển ở Đại La.. . Tư tưởng quy hoạch, tầm nhìn chiến lược thời Lý.. Trả lời sẽ nêu rõ mốc, diễn biến chính và",
    "story": "",
    "persons": [],
    "places": []
  },
  {
    "year": 1471,
    "event": "Đại Việt đánh bại Champa tại Vijaya (1471). Quân Đại Việt hạ kinh đô Vijaya của Champa. Sự kiện này có là Làm suy yếu Champa, mở rộng lãnh thổ về phương Nam",
    "story": "",
    "persons": [],
    "places": []
  },
  {
    "year": 1471,
    "event": "Câu hỏi nhắm tới sự kiện Đại Việt đánh bại Champa tại Vijaya (1471). Cốt lõi. Quân Đại Việt hạ kinh đô Vijaya của Champa.. . Làm suy yếu Champa, mở rộng lãnh thổ về phương Nam.. Trả lời sẽ nêu rõ mốc, diễn biến chính và",
    "story": "",
    "persons": [],
    "places": []
  },
  {
    "year": 1471,
    "event": "B1. gắn mốc 1471 với Đại Việt đánh bại Champa tại Vijaya. B2. nêu diễn biến trọng tâm – \"Quân Đại Việt hạ kinh đô Vijaya của Champa.\". B3. kết luận – Làm suy yếu Champa, mở rộng lãnh thổ về phương Nam",
    "story": "",
    "persons": [],
    "places": []
  },
  {
    "year": 1975,
    "event": "Câu hỏi nhắm tới sự kiện Chiến dịch Hồ Chí Minh – Giải phóng miền Nam (1975). Cốt lõi. Quân giải phóng tiến Sài Gòn ngày 30/4/1975.. . Thống nhất đất nước về lãnh thổ.. Trả lời sẽ nêu rõ mốc, diễn biến chính và",
    "story": "",
    "persons": [
      "Hồ Chí Minh"
    ],
    "places": [
      "Nam",
      "Sài Gòn"
    ]
  },
  {
    "year": 1975,
    "event": "Chiến dịch Hồ Chí Minh – Giải phóng miền Nam (1975). Quân giải phóng tiến Sài Gòn ngày 30/4/1975. Sự kiện này có là Thống nhất đất nước về lãnh thổ",
    "story": "",
    "persons": [
      "Hồ Chí Minh"
    ],
    "places": [
      "Nam",
      "Sài Gòn"
    ]
  },
  {
    "year": 1975,
    "event": "Bối cảnh. Chiến dịch Hồ Chí Minh – Giải phóng miền Nam thuộc Kết thúc chiến tranh, địa điểm Sài Gòn. Cốt lõi. Quân giải phóng tiến Sài Gòn ngày 30/4/1975.. . Thống nhất đất nước về lãnh thổ.. Sẽ tóm lược rõ ràng",
    "story": "",
    "persons": [
      "Hồ Chí Minh"
    ],
    "places": [
      "Sài Gòn"
    ]
  },
  {
    "year": 1975,
    "event": "B1. gắn mốc 1975 với Chiến dịch Hồ Chí Minh – Giải phóng miền Nam. B2. nêu diễn biến trọng tâm – \"Quân giải phóng tiến Sài Gòn ngày 30/4/1975.\". B3. kết luận – Thống nhất đất nước về lãnh thổ",
    "story": "",
    "persons": [
      "Hồ Chí Minh"
    ],
    "places": [
      "Nam",
      "Sài Gòn"
    ]
  },
  {
    "year": 1839,
    "event": "Đổi quốc hiệu Đại Nam thời Minh Mạng (1839). Triều Nguyễn dùng quốc hiệu Đại Nam dưới thời Minh Mạng. Sự kiện này có là Khẳng định chủ quyền và cơ cấu quản lý thống nhất",
    "story": "",
    "persons": [
      "Minh Mạng"
    ],
    "places": []
  },
  {
    "year": 1839,
    "event": "Câu hỏi nhắm tới sự kiện Đổi quốc hiệu Đại Nam thời Minh Mạng (1839). Cốt lõi. Triều Nguyễn dùng quốc hiệu Đại Nam dưới thời Minh Mạng.. . Khẳng định chủ quyền và cơ cấu quản lý thống nhất.. Trả lời sẽ nêu rõ mốc, diễn biến chính và",
    "story": "",
    "persons": [
      "Minh Mạng"
    ],
    "places": []
  },
  {
    "year": 1839,
    "event": "B1. gắn mốc 1839 với Đổi quốc hiệu Đại Nam thời Minh Mạng. B2. nêu diễn biến trọng tâm – \"Triều Nguyễn dùng quốc hiệu Đại Nam dưới thời Minh Mạng.\". B3. kết luận – Khẳng định chủ quyền và cơ cấu quản lý thống nhất",
    "story": "",
    "persons": [
      "Minh Mạng"
    ],
    "places": []
  },
  {
    "year": 1930,
    "event": "B1. gắn mốc 1930 với Khởi nghĩa Yên Bái. B2. nêu diễn biến trọng tâm – \"Việt Nam Quốc dân Đảng phát động khởi nghĩa chống Pháp tại Yên Bái.\". B3. kết luận – Tiêu biểu cho tinh thần yêu nước đầu thế kỷ XX, dù thất bại",
    "story": "",
    "persons": [],
    "places": []
  },
  {
    "year": 1930,
    "event": "Khởi nghĩa Yên Bái (1930). Việt Nam Quốc dân Đảng phát động khởi nghĩa chống Pháp tại Yên Bái. Sự kiện này có là Tiêu biểu cho tinh thần yêu nước đầu thế kỷ XX, dù thất bại",
    "story": "",
    "persons": [],
    "places": []
  },
  {
    "year": 1930,
    "event": "B1. gắn mốc 1930 với Thành lập Đảng Cộng sản Việt Nam. B2. nêu diễn biến trọng tâm – \"Hợp nhất các tổ chức cộng sản, xác lập đường lối cách mạng.\". B3. kết luận – Lãnh đạo phong trào đấu tranh giành độc lập",
    "story": "",
    "persons": [],
    "places": []
  },
  {
    "year": 1930,
    "event": "Thành lập Đảng Cộng sản Việt Nam (1930). Hợp nhất các tổ chức cộng sản, xác lập đường lối cách mạng. Sự kiện này có là Lãnh đạo phong trào đấu tranh giành độc lập",
    "story": "",
    "persons": [],
    "places": []
  },
  {
    "year": 1930,
    "event": "Câu hỏi nhắm tới sự kiện Thành lập Đảng Cộng sản Việt Nam (1930). Cốt lõi. Hợp nhất các tổ chức cộng sản, xác lập đường lối cách mạng.. . Lãnh đạo phong trào đấu tranh giành độc lập.. Trả lời sẽ nêu rõ mốc, diễn biến chính và",
    "story": "",
    "persons": [],
    "places": []
  },
  {
    "year": 1930,
    "event": "Câu hỏi nhắm tới sự kiện Khởi nghĩa Yên Bái (1930). Cốt lõi. Việt Nam Quốc dân Đảng phát động khởi nghĩa chống Pháp tại Yên Bái.. . Tiêu biểu cho tinh thần yêu nước đầu thế kỷ XX, dù thất bại.. Trả lời sẽ nêu rõ mốc, diễn biến chính và",
    "story": "",
    "persons": [],
    "places": []
  },
  {
    "year": 1460,
    "event": "Lê Thánh Tông trị vì (1460). Lê Thánh Tông đẩy mạnh cải cách, hoàn thiện bộ máy nhà nước. Sự kiện này có là Đỉnh cao thịnh trị của Lê sơ trên nhiều lĩnh vực",
    "story": "",
    "persons": [
      "Lê Thánh Tông"
    ],
    "places": []
  },
  {
    "year": 1460,
    "event": "B1. gắn mốc 1460 với Lê Thánh Tông trị vì. B2. nêu diễn biến trọng tâm – \"Lê Thánh Tông đẩy mạnh cải cách, hoàn thiện bộ máy nhà nước.\". B3. kết luận – Đỉnh cao thịnh trị của Lê sơ trên nhiều lĩnh vực",
    "story": "",
    "persons": [
      "Lê Thánh Tông"
    ],
    "places": []
  },
  {
    "year": 1460,
    "event": "Câu hỏi nhắm tới sự kiện Lê Thánh Tông trị vì (1460). Cốt lõi. Lê Thánh Tông đẩy mạnh cải cách, hoàn thiện bộ máy nhà nước.. . Đỉnh cao thịnh trị của Lê sơ trên nhiều lĩnh vực.. Trả lời sẽ nêu rõ mốc, diễn biến chính và",
    "story": "",
    "persons": [
      "Lê Thánh Tông"
    ],
    "places": []
  },
  {
    "year": 1960,
    "event": "Thành lập Mặt trận Dân tộc Giải phóng miền Nam (1960). Mặt trận ra đời nhằm đoàn kết lực lượng yêu nước ở miền Nam. Sự kiện này có là Tạo mặt trận chính trị – quân sự chống Mỹ và chính quyền Sài Gòn",
    "story": "",
    "persons": [],
    "places": [
      "Nam",
      "Sài Gòn"
    ]
  },
  {
    "year": 1960,
    "event": "B1. gắn mốc 1960 với Thành lập Mặt trận Dân tộc Giải phóng miền Nam. B2. nêu diễn biến trọng tâm – \"Mặt trận ra đời nhằm đoàn kết lực lượng yêu nước ở miền Nam.\". B3. kết luận – Tạo mặt trận chính trị – quân sự chống Mỹ và chính quyền Sài Gòn",
    "story": "",
    "persons": [],
    "places": [
      "Nam",
      "Sài Gòn"
    ]
  },
  {
    "year": 1960,
    "event": "Câu hỏi nhắm tới sự kiện Thành lập Mặt trận Dân tộc Giải phóng miền Nam (1960). Cốt lõi. Mặt trận ra đời nhằm đoàn kết lực lượng yêu nước ở miền Nam.. . Tạo mặt trận chính trị – quân sự chống Mỹ và chính quyền Sài Gòn.. Trả lời sẽ nêu rõ mốc, diễn biến chính và",
    "story": "",
    "persons": [],
    "places": [
      "Nam",
      "Sài Gòn"
    ]
  },
  {
    "year": 1954,
    "event": "Chiến thắng Điện Biên Phủ (1954). Quân đội Việt Nam giành thắng lợi quyết định tại Điện Biên Phủ. Sự kiện này có là Bước ngoặt lịch sử, dẫn tới Hiệp định Genève",
    "story": "",
    "persons": [],
    "places": [
      "Điện Biên Phủ"
    ]
  },
  {
    "year": 1954,
    "event": "Câu hỏi nhắm tới sự kiện Chiến thắng Điện Biên Phủ (1954). Cốt lõi. Quân đội Việt Nam giành thắng lợi quyết định tại Điện Biên Phủ.. . Bước ngoặt lịch sử, dẫn tới Hiệp định Genève.. Trả lời sẽ nêu rõ mốc, diễn biến chính và",
    "story": "",
    "persons": [],
    "places": [
      "Điện Biên Phủ"
    ]
  },
  {
    "year": 1954,
    "event": "Hiệp định Genève (1954). Ký Hiệp định Genève về chấm dứt chiến sự ở Việt Nam. Sự kiện này có là Tạm chia cắt đất nước ở vĩ tuyến 17, chuẩn bị tổng tuyển cử",
    "story": "",
    "persons": [],
    "places": []
  },
  {
    "year": 1954,
    "event": "Bối cảnh. Hình thành Việt Nam Cộng hòa ở miền Nam thuộc 1954–1975, địa điểm Sài Gòn. Cốt lõi. Miền Nam thành lập chính thể Việt Nam Cộng hòa.. . Củng cố tình trạng chia cắt đất nước.. Sẽ tóm lược rõ ràng",
    "story": "",
    "persons": [],
    "places": [
      "Sài Gòn"
    ]
  },
  {
    "year": 1954,
    "event": "Bối cảnh. Thành lập Mặt trận Dân tộc Giải phóng miền Nam thuộc 1954–1975, địa điểm Miền Nam. Cốt lõi. Mặt trận ra đời nhằm đoàn kết lực lượng yêu nước ở miền Nam.. . Tạo mặt trận chính trị – quân sự chống Mỹ và chính quyền Sài Gòn.. Sẽ tóm lược rõ ràng",
    "story": "",
    "persons": [],
    "places": [
      "Nam",
      "Sài Gòn"
    ]
  },
  {
    "year": 1954,
    "event": "Bối cảnh. Hiệp định Paris thuộc 1954–1975, địa điểm Paris. Cốt lõi. Hiệp định chấm dứt chiến tranh, lập lại hòa bình ở Việt Nam.. . Mỹ rút quân khỏi Việt Nam.. Sẽ tóm lược rõ ràng",
    "story": "",
    "persons": [],
    "places": []
  },
  {
    "year": 1954,
    "event": "Bối cảnh. Chiến dịch 'Điện Biên Phủ trên không' thuộc 1954–1975, địa điểm Miền Bắc. Cốt lõi. Quân dân miền Bắc đánh bại chiến dịch ném bom B-52 cuối 1972.. . Buộc Mỹ đàm phán, tiền đề Hiệp định Paris.. Sẽ tóm lược rõ ràng",
    "story": "",
    "persons": [],
    "places": [
      "Bắc",
      "Điện Biên Phủ"
    ]
  },
  {
    "year": 1954,
    "event": "Câu hỏi nhắm tới sự kiện Hiệp định Genève (1954). Cốt lõi. Ký Hiệp định Genève về chấm dứt chiến sự ở Việt Nam.. . Tạm chia cắt đất nước ở vĩ tuyến 17, chuẩn bị tổng tuyển cử.. Trả lời sẽ nêu rõ mốc, diễn biến chính và",
    "story": "",
    "persons": [],
    "places": []
  },
  {
    "year": 1954,
    "event": "B1. gắn mốc 1954 với Hiệp định Genève. B2. nêu diễn biến trọng tâm – \"Ký Hiệp định Genève về chấm dứt chiến sự ở Việt Nam.\". B3. kết luận – Tạm chia cắt đất nước ở vĩ tuyến 17, chuẩn bị tổng tuyển cử",
    "story": "",
    "persons": [],
    "places": []
  },
  {
    "year": 1954,
    "event": "Bối cảnh. Hiệp định Genève thuộc Sau 1954, địa điểm Giơ-ne-vơ. Cốt lõi. Ký Hiệp định Genève về chấm dứt chiến sự ở Việt Nam.. . Tạm chia cắt đất nước ở vĩ tuyến 17, chuẩn bị tổng tuyển cử.. Sẽ tóm lược rõ ràng",
    "story": "",
    "persons": [],
    "places": []
  },
  {
    "year": 1954,
    "event": "B1. gắn mốc 1954 với Chiến thắng Điện Biên Phủ. B2. nêu diễn biến trọng tâm – \"Quân đội Việt Nam giành thắng lợi quyết định tại Điện Biên Phủ.\". B3. kết luận – Bước ngoặt lịch sử, dẫn tới Hiệp định Genève",
    "story": "",
    "persons": [],
    "places": [
      "Điện Biên Phủ"
    ]
  },
  {
    "year": 1941,
    "event": "B1. gắn mốc 1941 với Việt Minh ra đời. B2. nêu diễn biến trọng tâm – \"Mặt trận Việt Nam Độc lập Đồng minh được thành lập, đoàn kết lực lượng cứu quốc.\". B3. kết luận – Tập hợp rộng rãi lực lượng chuẩn bị cho tổng khởi nghĩa",
    "story": "",
    "persons": [],
    "places": []
  },
  {
    "year": 1941,
    "event": "Việt Minh ra đời (1941). Mặt trận Việt Nam Độc lập Đồng minh được thành lập, đoàn kết lực lượng cứu quốc. Sự kiện này có là Tập hợp rộng rãi lực lượng chuẩn bị cho tổng khởi nghĩa",
    "story": "",
    "persons": [],
    "places": []
  },
  {
    "year": 1941,
    "event": "Câu hỏi nhắm tới sự kiện Việt Minh ra đời (1941). Cốt lõi. Mặt trận Việt Nam Độc lập Đồng minh được thành lập, đoàn kết lực lượng cứu quốc.. . Tập hợp rộng rãi lực lượng chuẩn bị cho tổng khởi nghĩa.. Trả lời sẽ nêu rõ mốc, diễn biến chính và",
    "story": "",
    "persons": [],
    "places": []
  },
  {
    "year": 2018,
    "event": "Câu hỏi nhắm tới sự kiện Ký kết CPTPP (2018). Cốt lõi. Tham gia Hiệp định Đối tác Toàn diện và Tiến bộ xuyên Thái Bình Dương.. . Mở rộng thị trường, nâng chuẩn thương mại.. Trả lời sẽ nêu rõ mốc, diễn biến chính và",
    "story": "",
    "persons": [],
    "places": []
  },
  {
    "year": 2018,
    "event": "Ký kết CPTPP (2018). Tham gia Hiệp định Đối tác Toàn diện và Tiến bộ xuyên Thái Bình Dương. Sự kiện này có là Mở rộng thị trường, nâng chuẩn thương mại",
    "story": "",
    "persons": [],
    "places": []
  },
  {
    "year": 2018,
    "event": "B1. gắn mốc 2018 với Ký kết CPTPP. B2. nêu diễn biến trọng tâm – \"Tham gia Hiệp định Đối tác Toàn diện và Tiến bộ xuyên Thái Bình Dương.\". B3. kết luận – Mở rộng thị trường, nâng chuẩn thương mại",
    "story": "",
    "persons": [],
    "places": []
  },
  {
    "year": 2018,
    "event": "diễn ra Ký kết CPTPP. Tham gia Hiệp định Đối tác Toàn diện và Tiến bộ xuyên Thái Bình Dương. . Mở rộng thị trường, nâng chuẩn thương mại",
    "story": "",
    "persons": [],
    "places": []
  },
  {
    "year": 2018,
    "event": "2018. Ký kết CPTPP. Tham gia Hiệp định Đối tác Toàn diện và Tiến bộ xuyên Thái Bình Dương. Mở rộng thị trường, nâng chuẩn thương mại",
    "story": "",
    "persons": [],
    "places": []
  },
  {
    "year": 1288,
    "event": "Trận Bạch Đằng (Trần Hưng Đạo) (1288). Trần Hưng Đạo nhử địch bãi cọc ngầm trên sông Bạch Đằng, tiêu diệt thủy quân Nguyên. Sự kiện này có là Đập tan ý đồ xâm lược, kết thúc chiến tranh, ghi dấu mốc chói lọi",
    "story": "",
    "persons": [
      "Trần Hưng Đạo"
    ],
    "places": [
      "Bạch Đằng"
    ]
  },
  {
    "year": 1288,
    "event": "Câu hỏi nhắm tới sự kiện Trận Bạch Đằng (Trần Hưng Đạo) (1288). Cốt lõi. Trần Hưng Đạo nhử địch bãi cọc ngầm trên sông Bạch Đằng, tiêu diệt thủy quân Nguyên.. . Đập tan ý đồ xâm lược, kết thúc chiến tranh, ghi dấu mốc chói lọi.. Trả lời sẽ nêu rõ mốc, diễn biến chính và",
    "story": "",
    "persons": [
      "Trần Hưng Đạo"
    ],
    "places": [
      "Bạch Đằng"
    ]
  },
  {
    "year": 1288,
    "event": "B1. gắn mốc 1288 với Trận Bạch Đằng (Trần Hưng Đạo). B2. nêu diễn biến trọng tâm – \"Trần Hưng Đạo nhử địch bãi cọc ngầm trên sông Bạch Đằng, tiêu diệt thủy quân Nguyên.\". B3. kết luận – Đập tan ý đồ xâm lược, kết thúc chiến tranh, ghi dấu mốc chói lọi",
    "story": "",
    "persons": [
      "Trần Hưng Đạo"
    ],
    "places": [
      "Bạch Đằng"
    ]
  },
  {
    "year": 981,
    "event": "Câu hỏi nhắm tới sự kiện Kháng Tống thắng lợi thời Lê Hoàn (981). Cốt lõi. Quân Đại Cồ Việt đánh lui quân Tống xâm lược.. . Bảo vệ nền độc lập non trẻ, khẳng định vị thế quốc gia.. Trả lời sẽ nêu rõ mốc, diễn biến chính và",
    "story": "",
    "persons": [
      "Lê Hoàn"
    ],
    "places": []
  },
  {
    "year": 981,
    "event": "Kháng Tống thắng lợi thời Lê Hoàn (981). Quân Đại Cồ Việt đánh lui quân Tống xâm lược. Sự kiện này có là Bảo vệ nền độc lập non trẻ, khẳng định vị thế quốc gia",
    "story": "",
    "persons": [
      "Lê Hoàn"
    ],
    "places": []
  },
  {
    "year": 981,
    "event": "B1. gắn mốc 981 với Kháng Tống thắng lợi thời Lê Hoàn. B2. nêu diễn biến trọng tâm – \"Quân Đại Cồ Việt đánh lui quân Tống xâm lược.\". B3. kết luận – Bảo vệ nền độc lập non trẻ, khẳng định vị thế quốc gia",
    "story": "",
    "persons": [],
    "places": []
  },
  {
    "year": 1285,
    "event": "Kháng chiến lần 2 chống Nguyên (1285). Quân dân Đại Việt giành thắng lợi lớn trước quân Nguyên. Sự kiện này có là Củng cố sức mạnh quốc gia và nghệ thuật chiến tranh nhân dân",
    "story": "",
    "persons": [],
    "places": []
  },
  {
    "year": 1285,
    "event": "Câu hỏi nhắm tới sự kiện Kháng chiến lần 2 chống Nguyên (1285). Cốt lõi. Quân dân Đại Việt giành thắng lợi lớn trước quân Nguyên.. . Củng cố sức mạnh quốc gia và nghệ thuật chiến tranh nhân dân.. Trả lời sẽ nêu rõ mốc, diễn biến chính và",
    "story": "",
    "persons": [],
    "places": []
  },
  {
    "year": 1285,
    "event": "B1. gắn mốc 1285 với Kháng chiến lần 2 chống Nguyên. B2. nêu diễn biến trọng tâm – \"Quân dân Đại Việt giành thắng lợi lớn trước quân Nguyên.\". B3. kết luận – Củng cố sức mạnh quốc gia và nghệ thuật chiến tranh nhân dân",
    "story": "",
    "persons": [],
    "places": []
  },
  {
    "year": 1955,
    "event": "Hình thành Việt Nam Cộng hòa ở miền Nam (1955). Miền Nam thành lập chính thể Việt Nam Cộng hòa. Sự kiện này có là Củng cố tình trạng chia cắt đất nước",
    "story": "",
    "persons": [],
    "places": [
      "Nam"
    ]
  },
  {
    "year": 1955,
    "event": "Câu hỏi nhắm tới sự kiện Hình thành Việt Nam Cộng hòa ở miền Nam (1955). Cốt lõi. Miền Nam thành lập chính thể Việt Nam Cộng hòa.. . Củng cố tình trạng chia cắt đất nước.. Trả lời sẽ nêu rõ mốc, diễn biến chính và",
    "story": "",
    "persons": [],
    "places": [
      "Nam"
    ]
  },
  {
    "year": 1955,
    "event": "B1. gắn mốc 1955 với Hình thành Việt Nam Cộng hòa ở miền Nam. B2. nêu diễn biến trọng tâm – \"Miền Nam thành lập chính thể Việt Nam Cộng hòa.\". B3. kết luận – Củng cố tình trạng chia cắt đất nước",
    "story": "",
    "persons": [],
    "places": [
      "Nam"
    ]
  },
  {
    "year": 1992,
    "event": "B1. gắn mốc 1992 với Hiến pháp 1992. B2. nêu diễn biến trọng tâm – \"Ban hành Hiến pháp phù hợp Đổi Mới.\". B3. kết luận – Khung pháp lý cho phát triển kinh tế – xã hội",
    "story": "",
    "persons": [],
    "places": []
  },
  {
    "year": 1992,
    "event": "Hiến pháp 1992 diễn ra năm 1992. . Ban hành Hiến pháp phù hợp Đổi Mới.. . Khung pháp lý cho phát triển kinh tế – xã hội",
    "story": "",
    "persons": [],
    "places": []
  },
  {
    "year": 1992,
    "event": "Câu hỏi nhắm tới sự kiện Hiến pháp 1992 (1992). Cốt lõi. Ban hành Hiến pháp phù hợp Đổi Mới.. . Khung pháp lý cho phát triển kinh tế – xã hội.. Trả lời sẽ nêu rõ mốc, diễn biến chính và",
    "story": "",
    "persons": [],
    "places": []
  },
  {
    "year": 1992,
    "event": "Hiến pháp 1992 (1992). Ban hành Hiến pháp phù hợp Đổi Mới. Sự kiện này có là Khung pháp lý cho phát triển kinh tế – xã hội",
    "story": "",
    "persons": [],
    "places": []
  },
  {
    "year": 1992,
    "event": "Bối cảnh. Hiến pháp 1992 thuộc Sau 1975, địa điểm Hà Nội. Cốt lõi. Ban hành Hiến pháp phù hợp Đổi Mới.. . Khung pháp lý cho phát triển kinh tế – xã hội.. Sẽ tóm lược rõ ràng",
    "story": "",
    "persons": [],
    "places": [
      "Hà Nội"
    ]
  },
  {
    "year": 1911,
    "event": "Nguyễn Tất Thành ra đi tìm đường cứu nước (1911). Nguyễn Tất Thành rời bến Nhà Rồng, bắt đầu hành trình qua nhiều châu lục. Sự kiện này có là Đặt nền móng cho con đường cách mạng sau này của Hồ Chí Minh",
    "story": "",
    "persons": [],
    "places": []
  },
  {
    "year": 1911,
    "event": "Câu hỏi nhắm tới sự kiện Nguyễn Tất Thành ra đi tìm đường cứu nước (1911). Cốt lõi. Nguyễn Tất Thành rời bến Nhà Rồng, bắt đầu hành trình qua nhiều châu lục.. . Đặt nền móng cho con đường cách mạng sau này của Hồ Chí Minh.. Trả lời sẽ nêu rõ mốc, diễn biến chính và",
    "story": "",
    "persons": [],
    "places": []
  },
  {
    "year": 1911,
    "event": "B1. gắn mốc 1911 với Nguyễn Tất Thành ra đi tìm đường cứu nước. B2. nêu diễn biến trọng tâm – \"Nguyễn Tất Thành rời bến Nhà Rồng, bắt đầu hành trình qua nhiều châu lục.\". B3. kết luận – Đặt nền móng cho con đường cách mạng sau này của Hồ Chí Minh",
    "story": "",
    "persons": [],
    "places": []
  },
  {
    "year": 1802,
    "event": "Nguyễn Ánh lên ngôi Gia Long, lập nhà Nguyễn (1802). Gia Long thống nhất đất nước sau khi đánh bại Tây Sơn. Sự kiện này có là Mở đầu triều Nguyễn – triều đại phong kiến cuối cùng",
    "story": "",
    "persons": [
      "Nguyễn Ánh"
    ],
    "places": []
  },
  {
    "year": 1802,
    "event": "B1. gắn mốc 1802 với Nguyễn Ánh lên ngôi Gia Long, lập nhà Nguyễn. B2. nêu diễn biến trọng tâm – \"Gia Long thống nhất đất nước sau khi đánh bại Tây Sơn.\". B3. kết luận – Mở đầu triều Nguyễn – triều đại phong kiến cuối cùng",
    "story": "",
    "persons": [
      "Nguyễn Ánh"
    ],
    "places": []
  },
  {
    "year": 1802,
    "event": "Câu hỏi nhắm tới sự kiện Nguyễn Ánh lên ngôi Gia Long, lập nhà Nguyễn (1802). Cốt lõi. Gia Long thống nhất đất nước sau khi đánh bại Tây Sơn.. . Mở đầu triều Nguyễn – triều đại phong kiến cuối cùng.. Trả lời sẽ nêu rõ mốc, diễn biến chính và",
    "story": "",
    "persons": [
      "Nguyễn Ánh"
    ],
    "places": []
  },
  {
    "year": 1009,
    "event": "Lý Công Uẩn được tôn lập (kết thúc Tiền Lê) diễn ra năm 1009. . Sau khi Lê Long Đĩnh qua đời, Lý Công Uẩn được tôn làm vua.. . Mở ra triều Lý với nhiều cải cách và thịnh trị",
    "story": "",
    "persons": [
      "Lý Thái Tổ"
    ],
    "places": []
  },
  {
    "year": 1009,
    "event": "B1. gắn mốc 1009 với Lý Công Uẩn được tôn lập (kết thúc Tiền Lê). B2. nêu diễn biến trọng tâm – \"Sau khi Lê Long Đĩnh qua đời, Lý Công Uẩn được tôn làm vua.\". B3. kết luận – Mở ra triều Lý với nhiều cải cách và thịnh trị",
    "story": "",
    "persons": [
      "Lý Thái Tổ"
    ],
    "places": []
  },
  {
    "year": 1009,
    "event": "Lý Công Uẩn được tôn lập (kết thúc Tiền Lê) (1009). Sau khi Lê Long Đĩnh qua đời, Lý Công Uẩn được tôn làm vua. Sự kiện này có là Mở ra triều Lý với nhiều cải cách và thịnh trị",
    "story": "",
    "persons": [
      "Lý Thái Tổ"
    ],
    "places": []
  },
  {
    "year": 1009,
    "event": "Câu hỏi nhắm tới sự kiện Lý Công Uẩn được tôn lập (kết thúc Tiền Lê) (1009). Cốt lõi. Sau khi Lê Long Đĩnh qua đời, Lý Công Uẩn được tôn làm vua.. . Mở ra triều Lý với nhiều cải cách và thịnh trị.. Trả lời sẽ nêu rõ mốc, diễn biến chính và",
    "story": "",
    "persons": [
      "Lý Thái Tổ"
    ],
    "places": []
  },
  {
    "year": 1407,
    "event": "Câu hỏi nhắm tới sự kiện Nhà Minh xâm lược, bắt đầu thời kỳ Minh thuộc (1407). Cốt lõi. Đại Việt rơi ách đô hộ của nhà Minh.. . Mở ra giai đoạn đấu tranh giải phóng khốc liệt.. Trả lời sẽ nêu rõ mốc, diễn biến chính và",
    "story": "",
    "persons": [],
    "places": []
  },
  {
    "year": 1407,
    "event": "Nhà Minh xâm lược, bắt đầu thời kỳ Minh thuộc diễn ra năm 1407. . Đại Việt rơi ách đô hộ của nhà Minh.. . Mở ra giai đoạn đấu tranh giải phóng khốc liệt",
    "story": "",
    "persons": [],
    "places": []
  },
  {
    "year": 1407,
    "event": "Nhà Minh xâm lược, bắt đầu thời kỳ Minh thuộc (1407). Đại Việt rơi ách đô hộ của nhà Minh. Sự kiện này có là Mở ra giai đoạn đấu tranh giải phóng khốc liệt",
    "story": "",
    "persons": [],
    "places": []
  },
  {
    "year": 1407,
    "event": "B1. gắn mốc 1407 với Nhà Minh xâm lược, bắt đầu thời kỳ Minh thuộc. B2. nêu diễn biến trọng tâm – \"Đại Việt rơi ách đô hộ của nhà Minh.\". B3. kết luận – Mở ra giai đoạn đấu tranh giải phóng khốc liệt",
    "story": "",
    "persons": [],
    "places": []
  },
  {
    "year": 1789,
    "event": "Ngọc Hồi – Đống Đa (Quang Trung) (1789). Quang Trung thần tốc tiến ra Bắc, đánh bại quân Thanh. Sự kiện này có là Bảo vệ độc lập, khẳng định tài thao lược quân sự",
    "story": "",
    "persons": [
      "Nguyễn Huệ"
    ],
    "places": [
      "Ngọc Hồi",
      "Đống Đa"
    ]
  },
  {
    "year": 1789,
    "event": "B1. gắn mốc 1789 với Ngọc Hồi – Đống Đa (Quang Trung). B2. nêu diễn biến trọng tâm – \"Quang Trung thần tốc tiến ra Bắc, đánh bại quân Thanh.\". B3. kết luận – Bảo vệ độc lập, khẳng định tài thao lược quân sự",
    "story": "",
    "persons": [
      "Nguyễn Huệ"
    ],
    "places": [
      "Ngọc Hồi",
      "Đống Đa"
    ]
  },
  {
    "year": 1789,
    "event": "Câu hỏi nhắm tới sự kiện Ngọc Hồi – Đống Đa (Quang Trung) (1789). Cốt lõi. Quang Trung thần tốc tiến ra Bắc, đánh bại quân Thanh.. . Bảo vệ độc lập, khẳng định tài thao lược quân sự.. Trả lời sẽ nêu rõ mốc, diễn biến chính và",
    "story": "",
    "persons": [
      "Nguyễn Huệ"
    ],
    "places": [
      "Ngọc Hồi",
      "Đống Đa"
    ]
  },
  {
    "year": 1905,
    "event": "Phong trào Đông Du (1905). Phan Bội Châu khởi xướng phong trào đưa thanh niên sang Nhật du học. Sự kiện này có là Tìm đường cứu nước theo con đường mới, tiếp thu tư tưởng và kỹ thuật hiện đại",
    "story": "",
    "persons": [
      "Phan Bội Châu"
    ],
    "places": []
  },
  {
    "year": 1905,
    "event": "Câu hỏi nhắm tới sự kiện Phong trào Đông Du (1905). Cốt lõi. Phan Bội Châu khởi xướng phong trào đưa thanh niên sang Nhật du học.. . Tìm đường cứu nước theo con đường mới, tiếp thu tư tưởng và kỹ thuật hiện đại.. Trả lời sẽ nêu rõ mốc, diễn biến chính và",
    "story": "",
    "persons": [
      "Phan Bội Châu"
    ],
    "places": []
  },
  {
    "year": 1905,
    "event": "B1. gắn mốc 1905 với Phong trào Đông Du. B2. nêu diễn biến trọng tâm – \"Phan Bội Châu khởi xướng phong trào đưa thanh niên sang Nhật du học.\". B3. kết luận – Tìm đường cứu nước theo con đường mới, tiếp thu tư tưởng và kỹ thuật hiện đại",
    "story": "",
    "persons": [
      "Phan Bội Châu"
    ],
    "places": []
  },
  {
    "year": 1527,
    "event": "B1. gắn mốc 1527 với Mạc Đăng Dung lập nhà Mạc. B2. nêu diễn biến trọng tâm – \"Mạc Đăng Dung soán ngôi, mở ra thời kỳ Nam–Bắc triều.\". B3. kết luận – Gây chia cắt chính trị kéo dài, xung đột với Lê trung hưng",
    "story": "",
    "persons": [
      "Mạc Đăng Dung"
    ],
    "places": []
  },
  {
    "year": 1527,
    "event": "Mạc Đăng Dung lập nhà Mạc diễn ra năm 1527. . Mạc Đăng Dung soán ngôi, mở ra thời kỳ Nam–Bắc triều.. . Gây chia cắt chính trị kéo dài, xung đột với Lê trung hưng",
    "story": "",
    "persons": [
      "Mạc Đăng Dung"
    ],
    "places": []
  },
  {
    "year": 1527,
    "event": "Câu hỏi nhắm tới sự kiện Mạc Đăng Dung lập nhà Mạc (1527). Cốt lõi. Mạc Đăng Dung soán ngôi, mở ra thời kỳ Nam–Bắc triều.. . Gây chia cắt chính trị kéo dài, xung đột với Lê trung hưng.. Trả lời sẽ nêu rõ mốc, diễn biến chính và",
    "story": "",
    "persons": [
      "Mạc Đăng Dung"
    ],
    "places": []
  },
  {
    "year": 1527,
    "event": "Mạc Đăng Dung lập nhà Mạc (1527). Mạc Đăng Dung soán ngôi, mở ra thời kỳ Nam–Bắc triều. Sự kiện này có là Gây chia cắt chính trị kéo dài, xung đột với Lê trung hưng",
    "story": "",
    "persons": [
      "Mạc Đăng Dung"
    ],
    "places": []
  },
  {
    "year": 1258,
    "event": "Kháng chiến lần 1 chống Mông Cổ (1258). Đại Việt đánh bại cuộc xâm lược đầu tiên của quân Mông Cổ. Sự kiện này có là Bảo vệ độc lập, mở ra chuỗi thắng lợi chống xâm lăng phương Bắc",
    "story": "",
    "persons": [],
    "places": []
  },
  {
    "year": 1258,
    "event": "B1. gắn mốc 1258 với Kháng chiến lần 1 chống Mông Cổ. B2. nêu diễn biến trọng tâm – \"Đại Việt đánh bại cuộc xâm lược đầu tiên của quân Mông Cổ.\". B3. kết luận – Bảo vệ độc lập, mở ra chuỗi thắng lợi chống xâm lăng phương Bắc",
    "story": "",
    "persons": [],
    "places": []
  },
  {
    "year": 1258,
    "event": "Câu hỏi nhắm tới sự kiện Kháng chiến lần 1 chống Mông Cổ (1258). Cốt lõi. Đại Việt đánh bại cuộc xâm lược đầu tiên của quân Mông Cổ.. . Bảo vệ độc lập, mở ra chuỗi thắng lợi chống xâm lăng phương Bắc.. Trả lời sẽ nêu rõ mốc, diễn biến chính và",
    "story": "",
    "persons": [],
    "places": []
  },
  {
    "year": 938,
    "event": "Trận Bạch Đằng (Ngô Quyền) (938). Ngô Quyền dùng cọc gỗ đặt ngầm trên sông Bạch Đằng, đánh bại thủy quân Nam Hán. Sự kiện này có là Chấm dứt hơn một thiên niên kỷ Bắc thuộc, mở ra kỷ nguyên độc lập của người Việt",
    "story": "",
    "persons": [
      "Ngô Quyền"
    ],
    "places": [
      "Bạch Đằng"
    ]
  },
  {
    "year": 938,
    "event": "Câu hỏi nhắm tới sự kiện Trận Bạch Đằng (Ngô Quyền) (938). Cốt lõi. Ngô Quyền dùng cọc gỗ đặt ngầm trên sông Bạch Đằng, đánh bại thủy quân Nam Hán.. . Chấm dứt hơn một thiên niên kỷ Bắc thuộc, mở ra kỷ nguyên độc lập của người Việt.. Trả lời sẽ nêu rõ mốc, diễn biến chính và",
    "story": "",
    "persons": [
      "Ngô Quyền"
    ],
    "places": [
      "Bạch Đằng"
    ]
  },
  {
    "year": 938,
    "event": "B1. gắn mốc 938 với Trận Bạch Đằng (Ngô Quyền). B2. nêu diễn biến trọng tâm – \"Ngô Quyền dùng cọc gỗ đặt ngầm trên sông Bạch Đằng, đánh bại thủy quân Nam Hán.\". B3. kết luận – Chấm dứt hơn một thiên niên kỷ Bắc thuộc, mở ra kỷ nguyên độc lập của người Việt",
    "story": "",
    "persons": [
      "Ngô Quyền"
    ],
    "places": [
      "Bạch Đằng"
    ]
  },
  {
    "year": 1483,
    "event": "B1. gắn mốc 1483 với Bộ luật Hồng Đức. B2. nêu diễn biến trọng tâm – \"Bộ luật Hồng Đức hoàn thiện dưới thời Lê Thánh Tông.\". B3. kết luận – Bộ luật tiêu biểu của Việt Nam thời phong kiến",
    "story": "",
    "persons": [
      "Lê Thánh Tông"
    ],
    "places": []
  },
  {
    "year": 1483,
    "event": "Bộ luật Hồng Đức (1483). Bộ luật Hồng Đức hoàn thiện dưới thời Lê Thánh Tông. Sự kiện này có là Bộ luật tiêu biểu của Việt Nam thời phong kiến",
    "story": "",
    "persons": [
      "Lê Thánh Tông"
    ],
    "places": []
  },
  {
    "year": 1483,
    "event": "Câu hỏi nhắm tới sự kiện Bộ luật Hồng Đức (1483). Cốt lõi. Bộ luật Hồng Đức hoàn thiện dưới thời Lê Thánh Tông.. . Bộ luật tiêu biểu của Việt Nam thời phong kiến.. Trả lời sẽ nêu rõ mốc, diễn biến chính và",
    "story": "",
    "persons": [
      "Lê Thánh Tông"
    ],
    "places": []
  },
  {
    "year": 939,
    "event": "Ngô Quyền xưng vương, đóng đô Cổ Loa (939). Sau chiến thắng Bạch Đằng, Ngô Quyền lên ngôi, chọn Cổ Loa làm kinh đô. Sự kiện này có là Xác lập quốc gia độc lập, khởi đầu nhà Ngô",
    "story": "",
    "persons": [
      "Ngô Quyền"
    ],
    "places": [
      "Bạch Đằng"
    ]
  },
  {
    "year": 939,
    "event": "Câu hỏi nhắm tới sự kiện Ngô Quyền xưng vương, đóng đô Cổ Loa (939). Cốt lõi. Sau chiến thắng Bạch Đằng, Ngô Quyền lên ngôi, chọn Cổ Loa làm kinh đô.. . Xác lập quốc gia độc lập, khởi đầu nhà Ngô.. Trả lời sẽ nêu rõ mốc, diễn biến chính và",
    "story": "",
    "persons": [
      "Ngô Quyền"
    ],
    "places": [
      "Bạch Đằng"
    ]
  },
  {
    "year": 939,
    "event": "B1. gắn mốc 939 với Ngô Quyền xưng vương, đóng đô Cổ Loa. B2. nêu diễn biến trọng tâm – \"Sau chiến thắng Bạch Đằng, Ngô Quyền lên ngôi, chọn Cổ Loa làm kinh đô.\". B3. kết luận – Xác lập quốc gia độc lập, khởi đầu nhà Ngô",
    "story": "",
    "persons": [
      "Ngô Quyền"
    ],
    "places": [
      "Bạch Đằng"
    ]
  },
  {
    "year": 1427,
    "event": "B1. gắn mốc 1427 với Toàn thắng chống Minh (Tốt Động–Chúc Động, Chi Lăng–Xương Giang). B2. nêu diễn biến trọng tâm – \"Nghĩa quân Lam Sơn giành thắng lợi quyết định, buộc quân Minh rút.\". B3. kết luận – Chấm dứt thời Minh thuộc, khôi phục độc lập",
    "story": "",
    "persons": [],
    "places": [
      "Chi Lăng",
      "Lam Sơn"
    ]
  },
  {
    "year": 1427,
    "event": "Câu hỏi nhắm tới sự kiện Toàn thắng chống Minh (Tốt Động–Chúc Động, Chi Lăng–Xương Giang) (1427). Cốt lõi. Nghĩa quân Lam Sơn giành thắng lợi quyết định, buộc quân Minh rút.. . Chấm dứt thời Minh thuộc, khôi phục độc lập.. Trả lời sẽ nêu rõ mốc, diễn biến chính và",
    "story": "",
    "persons": [],
    "places": [
      "Chi Lăng",
      "Lam Sơn"
    ]
  },
  {
    "year": 1785,
    "event": "Rạch Gầm – Xoài Mút (1785). Nguyễn Huệ đánh bại quân Xiêm trên sông Tiền. Sự kiện này có là Ngăn chặn can thiệp ngoại bang, củng cố Tây Sơn ở Nam Bộ",
    "story": "",
    "persons": [
      "Nguyễn Huệ"
    ],
    "places": [
      "Rạch Gầm",
      "Tiền",
      "Xoài Mút"
    ]
  },
  {
    "year": 1785,
    "event": "Câu hỏi nhắm tới sự kiện Rạch Gầm – Xoài Mút (1785). Cốt lõi. Nguyễn Huệ đánh bại quân Xiêm trên sông Tiền.. . Ngăn chặn can thiệp ngoại bang, củng cố Tây Sơn ở Nam Bộ.. Trả lời sẽ nêu rõ mốc, diễn biến chính và",
    "story": "",
    "persons": [
      "Nguyễn Huệ"
    ],
    "places": [
      "Rạch Gầm",
      "Tiền",
      "Xoài Mút"
    ]
  },
  {
    "year": 1785,
    "event": "B1. gắn mốc 1785 với Rạch Gầm – Xoài Mút. B2. nêu diễn biến trọng tâm – \"Nguyễn Huệ đánh bại quân Xiêm trên sông Tiền.\". B3. kết luận – Ngăn chặn can thiệp ngoại bang, củng cố Tây Sơn ở Nam Bộ",
    "story": "",
    "persons": [
      "Nguyễn Huệ"
    ],
    "places": [
      "Rạch Gầm",
      "Tiền",
      "Xoài Mút"
    ]
  },
  {
    "year": 1428,
    "event": "Lê Lợi lên ngôi, lập nhà Hậu Lê diễn ra năm 1428. . Lê Lợi xưng vương, ban Bình Ngô đại cáo tuyên cáo độc lập.. . Mở ra thời kỳ Lê sơ thịnh trị",
    "story": "",
    "persons": [
      "Lê Lợi"
    ],
    "places": []
  },
  {
    "year": 1428,
    "event": "Câu hỏi nhắm tới sự kiện Lê Lợi lên ngôi, lập nhà Hậu Lê (1428). Cốt lõi. Lê Lợi xưng vương, ban Bình Ngô đại cáo tuyên cáo độc lập.. . Mở ra thời kỳ Lê sơ thịnh trị.. Trả lời sẽ nêu rõ mốc, diễn biến chính và",
    "story": "",
    "persons": [
      "Lê Lợi"
    ],
    "places": []
  },
  {
    "year": 1428,
    "event": "Lê Lợi lên ngôi, lập nhà Hậu Lê (1428). Lê Lợi xưng vương, ban Bình Ngô đại cáo tuyên cáo độc lập. Sự kiện này có là Mở ra thời kỳ Lê sơ thịnh trị",
    "story": "",
    "persons": [
      "Lê Lợi"
    ],
    "places": []
  },
  {
    "year": 1428,
    "event": "B1. gắn mốc 1428 với Lê Lợi lên ngôi, lập nhà Hậu Lê. B2. nêu diễn biến trọng tâm – \"Lê Lợi xưng vương, ban Bình Ngô đại cáo tuyên cáo độc lập.\". B3. kết luận – Mở ra thời kỳ Lê sơ thịnh trị",
    "story": "",
    "persons": [
      "Lê Lợi"
    ],
    "places": []
  }
]